{
  "_id": "2485504628",
  "reply_to": "",
  "reply_level": "1",
  "name": "Hitaro",
  "url": "",
  "email": "5e0f5c37b858c71a60f26ddff68f1047",
  "date": "2016-01-29T20:43:50",
  "content": "این سوالیه که پاسخش خیلی وقته داده شده: پایتون؛ چون\n- کاراییش رو درزمینه اهداف آموزشی نشون داده: استنفورد، کورسرا، اِداِکس، یوداسیتی، خان‌آکادمی و ...، همگی از پایتون استفاده کرده‌اند و می کنند\n- منابع آموزشی فراوانی براش وجود داره: فیلم، کتاب، تمرین آنلاین و اینتراکتیو و...\n- بیش از دو دهه است که توسعه داده میشه\n- نه مثل C سطح پایینه، و نه کاملا کامپایلی: JIT؛ زبان‌های اسکریپتی (حتی چیزی مثل متلب) برای آموزش مناسبترند!\n- یادگیری پایتون لزوما زبان انگلیسی پیش نیازش نیست، چون منابع فارسی برای یادگیری مقدماتش به حد کافی موجوده: برنامه نویسی با پایتون | ۸۸۰۰ت | نشر دانشگاهی كيان\nو همین‌طور برنامه نويسي به زبان پايتون | ۱۲۰۰۰ت | جعفرنژاد قمی ؛ برای فراتر رفتن (در هر زبان برنامه نویسی)، بله انگلیسی لازمه اما در سطح انگلیسی‌ای عمومی وب کافیه، نه لزوما انگلیسی در حد کتابهای Advanced یا تافل. به این معنا نیست که نریم زبان انگلیسیمون رو تقویت کنیم. یادگیری هر زبان، یک سطح کیفیت زندگی شخص رو ارتقا میده.\n\n+ این که با هر زبانی میشه شروع به یادگیری کرد، حرفتون درسته، اما با بعضی زبانها میشه تمرکز بیشتری روی مفاهیم حفظ کرد. و پایتون مثل پاسکال، یکی از این زبانهاییه که تازه‌کار رو درگیر چیزایی که ممکنه C سرش بیاره، نمی‌کنه. \n\n* البته یک مورد نقض هم دیدم که Lynda.com برای آموزش مبانی برنامه‌نویسی از جاوااسکریپت استفاده کرده بود که البته اینم خوبه، برای کسی که می خواد فقط وارد صنعت وب بشه.\n* و خوب اگر پایتون رو انتخاب نمی کنند، حداقل سخت ترین زبان رو انتخاب نکنند: https://www.quora.com/Which-is-the-most-difficult-programming-language-to-learn-and-why"
}